moralesl/billing_alert/__init__.py
moralesl/billing_alert/py.typed
moralesl/billing_alert/_jsii/__init__.py
moralesl/billing_alert/_jsii/billing-alert@0.4.0.jsii.tgz
moralesl.billing_alert-0.4.0.dist-info/METADATA
moralesl.billing_alert-0.4.0.dist-info/WHEEL
moralesl.billing_alert-0.4.0.dist-info/top_level.txt
moralesl.billing_alert-0.4.0.dist-info/RECORD
