Metadata-Version: 2.1
Name: moralesl.billing-alert
Version: 0.4.0
Summary: Utility CDK construct to setup billing alerts easily
Home-page: https://github.com/moralesl/cdk-billing-alert.git
Author: Luis Morales
License: MIT
Project-URL: Source, https://github.com/moralesl/cdk-billing-alert.git
Platform: UNKNOWN
Classifier: Intended Audience :: Developers
Classifier: Operating System :: OS Independent
Classifier: Programming Language :: JavaScript
Classifier: Programming Language :: Python :: 3 :: Only
Classifier: Programming Language :: Python :: 3.6
Classifier: Programming Language :: Python :: 3.7
Classifier: Programming Language :: Python :: 3.8
Classifier: Typing :: Typed
Classifier: License :: OSI Approved
Requires-Python: >=3.6
Requires-Dist: jsii (~=1.2.0)
Requires-Dist: publication (>=0.0.3)
Requires-Dist: aws-cdk.aws-cloudwatch (==1.32.2)
Requires-Dist: aws-cdk.aws-cloudwatch-actions (==1.32.2)
Requires-Dist: aws-cdk.aws-sns (==1.32.2)
Requires-Dist: aws-cdk.aws-sns-subscriptions (==1.32.2)
Requires-Dist: aws-cdk.core (==1.32.2)
Requires-Dist: constructs (<3.0.0,>=2.0.0)
